tm_tc_code_generator/__init__.py
tm_tc_code_generator/main.py
tm_tc_code_generator/templates/package_initializer.jinja
tm_tc_code_generator/templates/pyproject.toml.jinja
tm_tc_code_generator/templates/telecommand_auto_source.jinja
tm_tc_code_generator/templates/telecommand_base_header.jinja
tm_tc_code_generator/templates/telecommand_base_source.jinja
tm_tc_code_generator/templates/telecommand_header.jinja
tm_tc_code_generator/templates/telecommand_python.jinja
tm_tc_code_generator/templates/telecommand_source.jinja
tm_tc_code_generator/templates/telemetry_auto_source.jinja
tm_tc_code_generator/templates/telemetry_base_header.jinja
tm_tc_code_generator/templates/telemetry_base_source.jinja
tm_tc_code_generator/templates/telemetry_header.jinja
tm_tc_code_generator/templates/telemetry_source.jinja
tm_tc_code_generator-0.10.1.dist-info/METADATA
tm_tc_code_generator-0.10.1.dist-info/WHEEL
tm_tc_code_generator-0.10.1.dist-info/entry_points.txt
tm_tc_code_generator-0.10.1.dist-info/licenses/LICENSE
tm_tc_code_generator-0.10.1.dist-info/RECORD
