Metadata-Version: 2.4
Name: tm-tc-code-generator
Version: 0.10.1
Summary: 
License-File: LICENSE
Author: Lautaro Mendieta
Author-email: lemendieta96@gmail.com
Requires-Python: >=3.10
Classifier: Programming Language :: Python :: 3
Classifier: Programming Language :: Python :: 3.10
Classifier: Programming Language :: Python :: 3.11
Classifier: Programming Language :: Python :: 3.12
Classifier: Programming Language :: Python :: 3.13
Classifier: Programming Language :: Python :: 3.14
Requires-Dist: click (>=8.3.0,<9.0.0)
Requires-Dist: jinja2 (>=3.1.6,<4.0.0)
